sidis/__init__.py
sidis/_nbdev.py
sidis/conversion.py
sidis/recursion.py
sidis/templates.py
sidis/utils.py
sidis-0.0.2.dist-info/LICENSE
sidis-0.0.2.dist-info/METADATA
sidis-0.0.2.dist-info/WHEEL
sidis-0.0.2.dist-info/entry_points.txt
sidis-0.0.2.dist-info/top_level.txt
sidis-0.0.2.dist-info/RECORD
