Metadata-Version: 2.1
Name: sidis
Version: 0.0.2
Summary: Simple Data Interfaces in Python
Home-page: https://github.com/Noeloikeau/sidis/tree/master/
Author: Noeloikeau
Author-email: charlot.5@osu.edu
License: Apache Software License 2.0
Keywords: Data,Science,Python
Platform: UNKNOWN
Classifier: Development Status :: 3 - Alpha
Classifier: Intended Audience :: Developers
Classifier: Natural Language :: English
Classifier: Programming Language :: Python :: 3.6
Classifier: Programming Language :: Python :: 3.7
Classifier: Programming Language :: Python :: 3.8
Classifier: License :: OSI Approved :: Apache Software License
Requires-Python: >=3.6
Requires-Dist: pip
Requires-Dist: packaging
Provides-Extra: dev
